ver3000-3.1.3.dist-info/METADATA
ver3000-3.1.3.dist-info/WHEEL
ver3000-3.1.3.dist-info/entry_points.txt
ver3000/__init__.py
ver3000/build_version.py
ver3000-3.1.3.dist-info/RECORD
