Metadata-Version: 2.1
Name: ver3000
Version: 3.1.3
Summary: Default template for PDM package
Author-Email: "D. Alex Graham" <alex@aode.space>
License: MIT
Requires-Python: >=3.13
